Sgaur_NCI_Lib.py
Sgaur_NCI_Lib-0.0.2.dist-info/METADATA
Sgaur_NCI_Lib-0.0.2.dist-info/WHEEL
Sgaur_NCI_Lib-0.0.2.dist-info/top_level.txt
Sgaur_NCI_Lib-0.0.2.dist-info/RECORD
