Metadata-Version: 2.1
Name: Sgaur_NCI_Lib
Version: 0.0.2
Summary: Sample Library for Laboratory Application
Author: Shubham Gaur NCI
Classifier: Programming Language :: Python :: 3
Classifier: License :: OSI Approved :: MIT License
Classifier: Operating System :: OS Independent
Requires-Python: >=3.6
